fastmarkup/__init__.py
fastmarkup/components.py
fastmarkup/elements.py
fastmarkup-0.1.dist-info/LICENSE
fastmarkup-0.1.dist-info/METADATA
fastmarkup-0.1.dist-info/WHEEL
fastmarkup-0.1.dist-info/top_level.txt
fastmarkup-0.1.dist-info/RECORD
