Metadata-Version: 2.1
Name: fastmarkup
Version: 0.1
Summary: A function-based HTML templating library
Home-page: https://github.com/pauloevpr/fastmarkup
Author: Paulo Souza
Author-email: paulo.roque@hey.com
License: MIT
Classifier: Development Status :: 3 - Alpha
Classifier: License :: OSI Approved :: MIT License
Classifier: Programming Language :: Python :: 3
License-File: LICENSE
